osmosis_proto/__init__.py
osmosis_proto/proto/__init__.py
osmosis_proto/proto/confio/__init__.py
osmosis_proto/proto/confio/proofs_pb2.py
osmosis_proto/proto/confio/proofs_pb2.pyi
osmosis_proto/proto/confio/proofs_pb2_grpc.py
osmosis_proto/proto/confio/proofs_pb2_grpc.pyi
osmosis_proto/proto/cosmos/__init__.py
osmosis_proto/proto/cosmos/auth/__init__.py
osmosis_proto/proto/cosmos/auth/v1beta1/__init__.py
osmosis_proto/proto/cosmos/auth/v1beta1/auth_pb2.py
osmosis_proto/proto/cosmos/auth/v1beta1/auth_pb2.pyi
osmosis_proto/proto/cosmos/auth/v1beta1/auth_pb2_grpc.py
osmosis_proto/proto/cosmos/auth/v1beta1/auth_pb2_grpc.pyi
osmosis_proto/proto/cosmos/auth/v1beta1/genesis_pb2.py
osmosis_proto/proto/cosmos/auth/v1beta1/genesis_pb2.pyi
osmosis_proto/proto/cosmos/auth/v1beta1/genesis_pb2_grpc.py
osmosis_proto/proto/cosmos/auth/v1beta1/genesis_pb2_grpc.pyi
osmosis_proto/proto/cosmos/auth/v1beta1/query_pb2.py
osmosis_proto/proto/cosmos/auth/v1beta1/query_pb2.pyi
osmosis_proto/proto/cosmos/auth/v1beta1/query_pb2_grpc.py
osmosis_proto/proto/cosmos/auth/v1beta1/query_pb2_grpc.pyi
osmosis_proto/proto/cosmos/authz/__init__.py
osmosis_proto/proto/cosmos/authz/v1beta1/__init__.py
osmosis_proto/proto/cosmos/authz/v1beta1/authz_pb2.py
osmosis_proto/proto/cosmos/authz/v1beta1/authz_pb2.pyi
osmosis_proto/proto/cosmos/authz/v1beta1/authz_pb2_grpc.py
osmosis_proto/proto/cosmos/authz/v1beta1/authz_pb2_grpc.pyi
osmosis_proto/proto/cosmos/authz/v1beta1/event_pb2.py
osmosis_proto/proto/cosmos/authz/v1beta1/event_pb2.pyi
osmosis_proto/proto/cosmos/authz/v1beta1/event_pb2_grpc.py
osmosis_proto/proto/cosmos/authz/v1beta1/event_pb2_grpc.pyi
osmosis_proto/proto/cosmos/authz/v1beta1/genesis_pb2.py
osmosis_proto/proto/cosmos/authz/v1beta1/genesis_pb2.pyi
osmosis_proto/proto/cosmos/authz/v1beta1/genesis_pb2_grpc.py
osmosis_proto/proto/cosmos/authz/v1beta1/genesis_pb2_grpc.pyi
osmosis_proto/proto/cosmos/authz/v1beta1/query_pb2.py
osmosis_proto/proto/cosmos/authz/v1beta1/query_pb2.pyi
osmosispy-0.0.9.dist-info/METADATA
osmosispy-0.0.9.dist-info/WHEEL
osmosispy-0.0.9.dist-info/RECORD
